plip2ml/__init__.py
plip2ml/plipxml2plipcsv.py
plip2ml/xml2csv.py
plip2ml-0.0.5.data/scripts/plip2ml-xml2csv
plip2ml-0.0.5.data/scripts/plipxml2plipcsv
plip2ml-0.0.5.dist-info/LICENSE
plip2ml-0.0.5.dist-info/METADATA
plip2ml-0.0.5.dist-info/WHEEL
plip2ml-0.0.5.dist-info/top_level.txt
plip2ml-0.0.5.dist-info/RECORD
